odoo8_addon_l10n_nl_chart_rgs-8.0.0.1.0.99.dev4-py2.7-nspkg.pth
odoo8_addon_l10n_nl_chart_rgs-8.0.0.1.0.99.dev4.dist-info/DESCRIPTION.rst
odoo8_addon_l10n_nl_chart_rgs-8.0.0.1.0.99.dev4.dist-info/METADATA
odoo8_addon_l10n_nl_chart_rgs-8.0.0.1.0.99.dev4.dist-info/RECORD
odoo8_addon_l10n_nl_chart_rgs-8.0.0.1.0.99.dev4.dist-info/WHEEL
odoo8_addon_l10n_nl_chart_rgs-8.0.0.1.0.99.dev4.dist-info/metadata.json
odoo8_addon_l10n_nl_chart_rgs-8.0.0.1.0.99.dev4.dist-info/namespace_packages.txt
odoo8_addon_l10n_nl_chart_rgs-8.0.0.1.0.99.dev4.dist-info/top_level.txt
odoo_addons/l10n_nl_chart_rgs/README.rst
odoo_addons/l10n_nl_chart_rgs/__init__.py
odoo_addons/l10n_nl_chart_rgs/__openerp__.py
odoo_addons/l10n_nl_chart_rgs/data/account_account_template.xml
odoo_addons/l10n_nl_chart_rgs/data/account_chart_template.xml
odoo_addons/l10n_nl_chart_rgs/data/account_fiscal_position_account_template.xml
odoo_addons/l10n_nl_chart_rgs/data/account_fiscal_position_tax_template.xml
odoo_addons/l10n_nl_chart_rgs/data/account_fiscal_position_template.xml
odoo_addons/l10n_nl_chart_rgs/data/account_tax_template.xml
odoo_addons/l10n_nl_chart_rgs/i18n/l10n_nl_chart_rgs.pot
odoo_addons/l10n_nl_chart_rgs/scripts/csv_to_chart_xml.py
odoo_addons/l10n_nl_chart_rgs/scripts/rgs2dot0.csv
odoo_addons/l10n_nl_chart_rgs/static/description/icon.png
