Metadata-Version: 2.0
Name: odoo8-addon-l10n-nl-chart-rgs
Version: 8.0.0.1.0.99.dev4
Summary: Netherlands - Accounting - Reference Accounting Scheme (RGS)
Home-page: https://github.com/OCA/l10n-netherlands
Author: Odoo Community Association (OCA), Therp BV
Author-email: support@odoo-community.org
License: AGPL-3
Platform: UNKNOWN
Classifier: Programming Language :: Python
Classifier: Framework :: Odoo
Classifier: License :: OSI Approved :: GNU Affero General Public License v3
Requires-Python: ~=2.7
Requires-Dist: odoo (<9.0a,>=8.0a)
